SQLAPI/__init__.py
SQLAPI_Timaos-0.0.1.dist-info/LICENSE
SQLAPI_Timaos-0.0.1.dist-info/METADATA
SQLAPI_Timaos-0.0.1.dist-info/WHEEL
SQLAPI_Timaos-0.0.1.dist-info/top_level.txt
SQLAPI_Timaos-0.0.1.dist-info/RECORD
