Metadata-Version: 2.1
Name: SQLAPI-Timaos
Version: 0.0.1
Summary: used to run certain kinds of sql in python
Home-page: https://github.com/Timaos123/SQLAPI
Author: Timaos
Author-email: 201436009@uibe.edu.cn
License: UNKNOWN
Platform: UNKNOWN
Classifier: Programming Language :: Python :: 3
Classifier: License :: OSI Approved :: MIT License
Classifier: Operating System :: OS Independent
Requires-Python: >=3.6
